spare/.gitignore
spare/__init__.py
spare/backup.py
spare/block.py
spare/cli.py
spare/download.py
spare/envoy.py
spare/errors.py
spare/inventory.py
spare/recovery.py
spare/snapshot.py
spare/utils.py
spare/tests/conftest.py
spare/tests/test_backup.py
spare/tests/test_block.py
spare/tests/test_cli.py
spare/tests/test_download.py
spare/tests/test_envoy.py
spare/tests/test_inventory.py
spare/tests/test_snapshot.py
spare/tests/test_transfer.py
spare/tests/test_utils.py
spare-0.4.0.dist-info/LICENSE
spare-0.4.0.dist-info/METADATA
spare-0.4.0.dist-info/WHEEL
spare-0.4.0.dist-info/entry_points.txt
spare-0.4.0.dist-info/namespace_packages.txt
spare-0.4.0.dist-info/top_level.txt
spare-0.4.0.dist-info/RECORD
