Metadata-Version: 2.1
Name: spare
Version: 0.4.0
Summary: One S3 backup, encrypted on the fly.
Home-page: http://github.com/seantis/spare
Author: Seantis GmbH
Author-email: info@seantis.ch
License: MIT
Platform: any
Classifier: Intended Audience :: System Administrators
Classifier: License :: OSI Approved :: MIT License
Classifier: Operating System :: Unix
Classifier: Programming Language :: Python :: 3
Classifier: Topic :: System :: Archiving :: Backup
Requires-Python: >=3.6.2
Requires-Dist: boto3
Requires-Dist: cached-property
Requires-Dist: click
Requires-Dist: cryptography
Requires-Dist: logbook
Requires-Dist: miscreant
Requires-Dist: ulid-py
Provides-Extra: test
Requires-Dist: hypothesis ; extra == 'test'
Requires-Dist: mirakuru ; extra == 'test'
Requires-Dist: flake8 ; extra == 'test'
Requires-Dist: port-for ; extra == 'test'
Requires-Dist: pytest ; extra == 'test'
Requires-Dist: pytest-cov ; extra == 'test'
Requires-Dist: pytest-flake8 ; extra == 'test'
Requires-Dist: pytest-logbook ; extra == 'test'
